django_file/__init__.py
django_file/admin.py
django_file/models.py
django_file/tests.py
django_file/urls.py
django_file/views.py
django_file-1.0.6.dist-info/METADATA
django_file-1.0.6.dist-info/WHEEL
django_file-1.0.6.dist-info/top_level.txt
django_file-1.0.6.dist-info/RECORD
