Metadata-Version: 2.1
Name: django-file
Version: 1.0.6
Summary: Django File Relative
Home-page: https://github.com/django-xxx/django-file
Author: Hackathon
Author-email: kimi.huang@brightcells.com
Keywords: Django File
Classifier: Development Status :: 5 - Production/Stable
Classifier: Environment :: Web Environment
Classifier: Framework :: Django
Classifier: Intended Audience :: Developers
Classifier: Programming Language :: Python
Classifier: Topic :: Software Development :: Libraries :: Python Modules
Classifier: Topic :: Office/Business :: Financial :: Spreadsheet
Requires-Dist: django-file-download (>=1.0.1)
Requires-Dist: django-file-md5 (>=1.0.3)
Requires-Dist: django-file-upload
